constrainedrandom/__init__.py
constrainedrandom/bits.py
constrainedrandom/debug.py
constrainedrandom/randobj.py
constrainedrandom/random.py
constrainedrandom/utils.py
constrainedrandom/internal/__init__.py
constrainedrandom/internal/multivar.py
constrainedrandom/internal/randvar.py
constrainedrandom/internal/vargroup.py
constrainedrandom-1.2.2.dist-info/METADATA
constrainedrandom-1.2.2.dist-info/WHEEL
constrainedrandom-1.2.2.dist-info/licenses/LICENSE
constrainedrandom-1.2.2.dist-info/RECORD
