Metadata-Version: 2.3
Name: constrainedrandom
Version: 1.2.2
Summary: A library for creating and solving constrained randomization problems
Project-URL: Homepage, https://github.com/will-keen/constrainedrandom
Project-URL: Bug Tracker, https://github.com/will-keen/constrainedrandom/issues
Author-email: Will Keen <willkeencodes@gmail.com>
License: MIT License
License-File: LICENSE
Keywords: constrained,constraint,random,randomization,verification
Classifier: License :: OSI Approved :: MIT License
Classifier: Programming Language :: Python :: 3
Classifier: Topic :: Scientific/Engineering
Requires-Python: >=3.8.3
Requires-Dist: python-constraint>=1.4.0
